{
  "openapi": "3.0.1",
  "info": {
    "title": "Dosya Yonetim Sistemi Api",
    "description": "An ASP.NET Core Web API with JWT Authentication",
    "version": "v1"
  },
  "paths": {
    "/api/Admin/users": {
      "get": {
        "tags": [
          "Admin"
        ],
        "summary": "Gets all users in the system",
        "responses": {
          "200": {
            "description": "Success"
          }
        }
      }
    },
    "/api/Admin/users/{userId}/storage": {
      "put": {
        "tags": [
          "Admin"
        ],
        "summary": "Updates a user's storage limit",
        "parameters": [
          {
            "name": "userId",
            "in": "path",
            "description": "The ID of the user",
            "required": true,
            "style": "simple",
            "schema": {
              "type": "string"
            }
          }
        ],
        "requestBody": {
          "description": "New storage limit in bytes",
          "content": {
            "application/json": {
              "schema": {
                "$ref": "#/components/schemas/UserStorageUpdateDTO"
              }
            },
            "text/json": {
              "schema": {
                "$ref": "#/components/schemas/UserStorageUpdateDTO"
              }
            },
            "application/*+json": {
              "schema": {
                "$ref": "#/components/schemas/UserStorageUpdateDTO"
              }
            }
          }
        },
        "responses": {
          "200": {
            "description": "Success"
          }
        }
      }
    },
    "/api/Admin/users/{userId}/assign-admin": {
      "post": {
        "tags": [
          "Admin"
        ],
        "summary": "Assigns admin role to a user",
        "parameters": [
          {
            "name": "userId",
            "in": "path",
            "description": "The ID of the user",
            "required": true,
            "style": "simple",
            "schema": {
              "type": "string"
            }
          }
        ],
        "responses": {
          "200": {
            "description": "Success"
          }
        }
      }
    },
    "/api/Admin/users/{userId}/remove-admin": {
      "post": {
        "tags": [
          "Admin"
        ],
        "summary": "Removes admin role from a user",
        "parameters": [
          {
            "name": "userId",
            "in": "path",
            "description": "The ID of the user",
            "required": true,
            "style": "simple",
            "schema": {
              "type": "string"
            }
          }
        ],
        "responses": {
          "200": {
            "description": "Success"
          }
        }
      }
    },
    "/api/Admin/storage": {
      "get": {
        "tags": [
          "Admin"
        ],
        "summary": "Gets storage details for all users",
        "responses": {
          "200": {
            "description": "Success"
          }
        }
      }
    },
    "/api/Admin/active-storage": {
      "get": {
        "tags": [
          "Admin"
        ],
        "summary": "Gets active user storage details",
        "responses": {
          "200": {
            "description": "Success"
          }
        }
      }
    },
    "/api/Auth/register": {
      "post": {
        "tags": [
          "Auth"
        ],
        "summary": "Registers a new user",
        "requestBody": {
          "description": "User registration details",
          "content": {
            "application/json": {
              "schema": {
                "$ref": "#/components/schemas/RegisterDto"
              }
            },
            "text/json": {
              "schema": {
                "$ref": "#/components/schemas/RegisterDto"
              }
            },
            "application/*+json": {
              "schema": {
                "$ref": "#/components/schemas/RegisterDto"
              }
            }
          }
        },
        "responses": {
          "200": {
            "description": "Returns the newly created user"
          },
          "400": {
            "description": "If the registration fails",
            "content": {
              "text/plain": {
                "schema": {
                  "$ref": "#/components/schemas/ProblemDetails"
                }
              },
              "application/json": {
                "schema": {
                  "$ref": "#/components/schemas/ProblemDetails"
                }
              },
              "text/json": {
                "schema": {
                  "$ref": "#/components/schemas/ProblemDetails"
                }
              }
            }
          }
        }
      }
    },
    "/api/Auth/login": {
      "post": {
        "tags": [
          "Auth"
        ],
        "summary": "Authenticates a user",
        "requestBody": {
          "description": "Login credentials",
          "content": {
            "application/json": {
              "schema": {
                "$ref": "#/components/schemas/LoginDto"
              }
            },
            "text/json": {
              "schema": {
                "$ref": "#/components/schemas/LoginDto"
              }
            },
            "application/*+json": {
              "schema": {
                "$ref": "#/components/schemas/LoginDto"
              }
            }
          }
        },
        "responses": {
          "200": {
            "description": "Returns the JWT token"
          },
          "400": {
            "description": "If the login fails",
            "content": {
              "text/plain": {
                "schema": {
                  "$ref": "#/components/schemas/ProblemDetails"
                }
              },
              "application/json": {
                "schema": {
                  "$ref": "#/components/schemas/ProblemDetails"
                }
              },
              "text/json": {
                "schema": {
                  "$ref": "#/components/schemas/ProblemDetails"
                }
              }
            }
          }
        }
      }
    },
    "/api/Auth/register-admin": {
      "post": {
        "tags": [
          "Auth"
        ],
        "requestBody": {
          "content": {
            "application/json": {
              "schema": {
                "$ref": "#/components/schemas/RegisterDto"
              }
            },
            "text/json": {
              "schema": {
                "$ref": "#/components/schemas/RegisterDto"
              }
            },
            "application/*+json": {
              "schema": {
                "$ref": "#/components/schemas/RegisterDto"
              }
            }
          }
        },
        "responses": {
          "200": {
            "description": "Success"
          }
        }
      }
    },
    "/api/Auth/current-user": {
      "get": {
        "tags": [
          "Auth"
        ],
        "responses": {
          "200": {
            "description": "Success"
          }
        }
      }
    },
    "/api/File/{id}": {
      "get": {
        "tags": [
          "File"
        ],
        "parameters": [
          {
            "name": "id",
            "in": "path",
            "required": true,
            "style": "simple",
            "schema": {
              "type": "integer",
              "format": "int32"
            }
          }
        ],
        "responses": {
          "200": {
            "description": "Success"
          }
        }
      },
      "delete": {
        "tags": [
          "File"
        ],
        "parameters": [
          {
            "name": "id",
            "in": "path",
            "required": true,
            "style": "simple",
            "schema": {
              "type": "integer",
              "format": "int32"
            }
          }
        ],
        "responses": {
          "200": {
            "description": "Success"
          }
        }
      }
    },
    "/api/File/folder/{folderId}": {
      "get": {
        "tags": [
          "File"
        ],
        "parameters": [
          {
            "name": "folderId",
            "in": "path",
            "required": true,
            "style": "simple",
            "schema": {
              "type": "integer",
              "format": "int32"
            }
          }
        ],
        "responses": {
          "200": {
            "description": "Success"
          }
        }
      }
    },
    "/api/File/upload": {
      "post": {
        "tags": [
          "File"
        ],
        "parameters": [
          {
            "name": "folderId",
            "in": "query",
            "style": "form",
            "schema": {
              "type": "integer",
              "format": "int32"
            }
          }
        ],
        "requestBody": {
          "content": {
            "multipart/form-data": {
              "schema": {
                "type": "object",
                "properties": {
                  "file": {
                    "type": "string",
                    "format": "binary"
                  }
                }
              },
              "encoding": {
                "file": {
                  "style": "form"
                }
              }
            }
          }
        },
        "responses": {
          "200": {
            "description": "Success"
          }
        }
      }
    },
    "/api/File/{id}/download": {
      "get": {
        "tags": [
          "File"
        ],
        "parameters": [
          {
            "name": "id",
            "in": "path",
            "required": true,
            "style": "simple",
            "schema": {
              "type": "integer",
              "format": "int32"
            }
          }
        ],
        "responses": {
          "200": {
            "description": "Success"
          }
        }
      }
    },
    "/api/File/search": {
      "get": {
        "tags": [
          "File"
        ],
        "parameters": [
          {
            "name": "searchTerm",
            "in": "query",
            "style": "form",
            "schema": {
              "type": "string"
            }
          }
        ],
        "responses": {
          "200": {
            "description": "Success"
          }
        }
      }
    },
    "/api/File/recent": {
      "get": {
        "tags": [
          "File"
        ],
        "parameters": [
          {
            "name": "count",
            "in": "query",
            "style": "form",
            "schema": {
              "type": "integer",
              "format": "int32",
              "default": 10
            }
          }
        ],
        "responses": {
          "200": {
            "description": "Success"
          }
        }
      }
    },
    "/api/File/type/{fileType}": {
      "get": {
        "tags": [
          "File"
        ],
        "parameters": [
          {
            "name": "fileType",
            "in": "path",
            "required": true,
            "style": "simple",
            "schema": {
              "type": "string"
            }
          }
        ],
        "responses": {
          "200": {
            "description": "Success"
          }
        }
      }
    },
    "/api/File/simple-download/{id}": {
      "get": {
        "tags": [
          "File"
        ],
        "parameters": [
          {
            "name": "id",
            "in": "path",
            "required": true,
            "style": "simple",
            "schema": {
              "type": "integer",
              "format": "int32"
            }
          }
        ],
        "responses": {
          "200": {
            "description": "Success"
          }
        }
      }
    },
    "/api/Folder": {
      "get": {
        "tags": [
          "Folder"
        ],
        "responses": {
          "200": {
            "description": "Success"
          }
        }
      },
      "post": {
        "tags": [
          "Folder"
        ],
        "requestBody": {
          "content": {
            "application/json": {
              "schema": {
                "$ref": "#/components/schemas/FolderCreateDTO"
              }
            },
            "text/json": {
              "schema": {
                "$ref": "#/components/schemas/FolderCreateDTO"
              }
            },
            "application/*+json": {
              "schema": {
                "$ref": "#/components/schemas/FolderCreateDTO"
              }
            }
          }
        },
        "responses": {
          "200": {
            "description": "Success"
          }
        }
      }
    },
    "/api/Folder/{id}": {
      "get": {
        "tags": [
          "Folder"
        ],
        "parameters": [
          {
            "name": "id",
            "in": "path",
            "required": true,
            "style": "simple",
            "schema": {
              "type": "integer",
              "format": "int32"
            }
          }
        ],
        "responses": {
          "200": {
            "description": "Success"
          }
        }
      },
      "put": {
        "tags": [
          "Folder"
        ],
        "parameters": [
          {
            "name": "id",
            "in": "path",
            "required": true,
            "style": "simple",
            "schema": {
              "type": "integer",
              "format": "int32"
            }
          }
        ],
        "requestBody": {
          "content": {
            "application/json": {
              "schema": {
                "$ref": "#/components/schemas/FolderUpdateDTO"
              }
            },
            "text/json": {
              "schema": {
                "$ref": "#/components/schemas/FolderUpdateDTO"
              }
            },
            "application/*+json": {
              "schema": {
                "$ref": "#/components/schemas/FolderUpdateDTO"
              }
            }
          }
        },
        "responses": {
          "200": {
            "description": "Success"
          }
        }
      },
      "delete": {
        "tags": [
          "Folder"
        ],
        "parameters": [
          {
            "name": "id",
            "in": "path",
            "required": true,
            "style": "simple",
            "schema": {
              "type": "integer",
              "format": "int32"
            }
          }
        ],
        "responses": {
          "200": {
            "description": "Success"
          }
        }
      }
    },
    "/api/Folder/search": {
      "get": {
        "tags": [
          "Folder"
        ],
        "parameters": [
          {
            "name": "searchTerm",
            "in": "query",
            "style": "form",
            "schema": {
              "type": "string"
            }
          }
        ],
        "responses": {
          "200": {
            "description": "Success"
          }
        }
      }
    },
    "/api/Folder/{id}/size": {
      "get": {
        "tags": [
          "Folder"
        ],
        "parameters": [
          {
            "name": "id",
            "in": "path",
            "required": true,
            "style": "simple",
            "schema": {
              "type": "integer",
              "format": "int32"
            }
          }
        ],
        "responses": {
          "200": {
            "description": "Success"
          }
        }
      }
    }
  },
  "components": {
    "schemas": {
      "FolderCreateDTO": {
        "type": "object",
        "properties": {
          "name": {
            "type": "string",
            "nullable": true
          }
        },
        "additionalProperties": false
      },
      "FolderUpdateDTO": {
        "type": "object",
        "properties": {
          "name": {
            "type": "string",
            "nullable": true
          }
        },
        "additionalProperties": false
      },
      "LoginDto": {
        "required": [
          "password",
          "username"
        ],
        "type": "object",
        "properties": {
          "username": {
            "minLength": 1,
            "type": "string"
          },
          "password": {
            "minLength": 1,
            "type": "string"
          }
        },
        "additionalProperties": false
      },
      "ProblemDetails": {
        "type": "object",
        "properties": {
          "type": {
            "type": "string",
            "nullable": true
          },
          "title": {
            "type": "string",
            "nullable": true
          },
          "status": {
            "type": "integer",
            "format": "int32",
            "nullable": true
          },
          "detail": {
            "type": "string",
            "nullable": true
          },
          "instance": {
            "type": "string",
            "nullable": true
          }
        },
        "additionalProperties": { }
      },
      "RegisterDto": {
        "required": [
          "email",
          "firstName",
          "lastName",
          "password",
          "username"
        ],
        "type": "object",
        "properties": {
          "firstName": {
            "minLength": 1,
            "type": "string"
          },
          "lastName": {
            "minLength": 1,
            "type": "string"
          },
          "email": {
            "minLength": 1,
            "type": "string",
            "format": "email"
          },
          "username": {
            "minLength": 6,
            "type": "string"
          },
          "password": {
            "minLength": 6,
            "type": "string"
          }
        },
        "additionalProperties": false
      },
      "UserStorageUpdateDTO": {
        "type": "object",
        "properties": {
          "totalStorage": {
            "type": "integer",
            "format": "int64"
          }
        },
        "additionalProperties": false
      }
    },
    "securitySchemes": {
      "Bearer": {
        "type": "apiKey",
        "description": "JWT Authorization header using the Bearer scheme. \r\n\r\n Enter 'Bearer' [space] and then your token in the text input below.\r\n\r\nExample: \"Bearer 12345abcdef\"",
        "name": "Authorization",
        "in": "header"
      }
    }
  },
  "security": [
    {
      "Bearer": [ ]
    }
  ]
}